Workbook

Sheet 月次サマリー
A1: 月次サマリー
A3: ■ 売上
A4: 請求済合計（税込） | B4: =SUM(売上管理!G2:G201)
A5: 入金済合計 | B5: =SUMIF(売上管理!L2:L201,"入金済",売上管理!K2:K201)
A6: 未入金残高 | B6: =SUMIF(売上管理!L2:L201,"未入金",売上管理!G2:G201)
A8: ■ 外注費
A9: 請求受取合計（税込） | B9: =SUM(外注管理!H2:H201)
A10: 支払済合計 | B10: =SUMIF(外注管理!M2:M201,"支払済",外注管理!L2:L201)
A11: 未払残高 | B11: =SUMIF(外注管理!M2:M201,"未払",外注管理!H2:H201)
A13: ■ 経費
A14: 材料費 | B14: =SUMIF(経費!C2:C201,"材料費",経費!G2:G201)
A15: 燃料費 | B15: =SUMIF(経費!C2:C201,"燃料費",経費!G2:G201)
A16: 高速料金 | B16: =SUMIF(経費!C2:C201,"高速料金",経費!G2:G201)
A17: 駐車場代 | B17: =SUMIF(経費!C2:C201,"駐車場代",経費!G2:G201)
A18: 工具・消耗品費 | B18: =SUMIF(経費!C2:C201,"工具・消耗品費",経費!G2:G201)
A19: 通信費 | B19: =SUMIF(経費!C2:C201,"通信費",経費!G2:G201)
A20: 交際費 | B20: =SUMIF(経費!C2:C201,"交際費",経費!G2:G201)
A21: 会議費 | B21: =SUMIF(経費!C2:C201,"会議費",経費!G2:G201)
A22: 事務用品費 | B22: =SUMIF(経費!C2:C201,"事務用品費",経費!G2:G201)
A23: 広告宣伝費 | B23: =SUMIF(経費!C2:C201,"広告宣伝費",経費!G2:G201)
A24: 研修費 | B24: =SUMIF(経費!C2:C201,"研修費",経費!G2:G201)
A25: 福利厚生費 | B25: =SUMIF(経費!C2:C201,"福利厚生費",経費!G2:G201)
A26: 車両維持費 | B26: =SUMIF(経費!C2:C201,"車両維持費",経費!G2:G201)
A27: 地代家賃 | B27: =SUMIF(経費!C2:C201,"地代家賃",経費!G2:G201)
A28: 保険料 | B28: =SUMIF(経費!C2:C201,"保険料",経費!G2:G201)
A29: 雑費 | B29: =SUMIF(経費!C2:C201,"雑費",経費!G2:G201)
A30: 経費合計 | B30: =SUM(経費!G2:G201)
A32: ■ 人件費
A33: 支給総額合計 | B33: =SUM(人件費!B2:B14)
A34: 手取り合計 | B34: =SUM(人件費!D2:D14)
A36: ■ 粗利（概算）
A37: =SUM(売上管理!G2:G201)-SUM(外注管理!H2:H201)-SUM(経費!G2:G201)-SUM(人件費!B2:B14)

Sheet 経費
A1: No | B1: 日付 | C1: 経費種類 | D1: 支払方法 | E1: 店名・支払先 | F1: 案件名 | G1: 金額（税込） | H1: 備考
A2: =IF(B2<>"",ROW()-1,"")
A3: =IF(B3<>"",ROW()-1,"")
A4: =IF(B4<>"",ROW()-1,"")
A5: =IF(B5<>"",ROW()-1,"")
A6: =IF(B6<>"",ROW()-1,"")
A7: =IF(B7<>"",ROW()-1,"")
A8: =IF(B8<>"",ROW()-1,"")
A9: =IF(B9<>"",ROW()-1,"")
A10: =IF(B10<>"",ROW()-1,"")
A11: =IF(B11<>"",ROW()-1,"")
A12: =IF(B12<>"",ROW()-1,"")
A13: =IF(B13<>"",ROW()-1,"")
... A201: =IF(B201<>"",ROW()-1,"")
F202: 合計 | G202: =SUM(G2:G201)

Sheet 外注管理
A1: No | B1: 登録日 | C1: 業者名 | D1: 種別 | E1: インボイス | F1: 案件名 | G1: 請求額(税抜) | H1: 消費税(10%) | I1: 合計(税込) | J1: 請求日 | K1: 支払期限 | L1: 支払日 | M1: 支払額 | N1: 状況
A2: =IF(C2<>"",ROW()-1,"") | D2: =IF(C2="","",IFERROR(VLOOKUP(C2,マスター!A:B,2,0),"")) | E2: =IF(C2="","",IFERROR(VLOOKUP(C2,マスター!A:C,3,0),"")) | H2: =IF(G2="","",G2*0.1) | I2: =IF(G2="","",G2+H2) | K2: =IF(J2="","",EOMONTH(J2,1)) | N2: =IF(C2="","",IF(L2<>"","支払済","未払"))
A3: =IF(C3<>"",ROW()-1,"") | D3: =IF(C3="","",IFERROR(VLOOKUP(C3,マスター!A:B,2,0),"")) | E3: =IF(C3="","",IFERROR(VLOOKUP(C3,マスター!A:C,3,0),"")) | H3: =IF(G3="","",G3*0.1) | I3: =IF(G3="","",G3+H3) | K3: =IF(J3="","",EOMONTH(J3,1)) | N3: =IF(C3="","",IF(L3<>"","支払済","未払"))
A4: =IF(C4<>"",ROW()-1,"") | D4: =IF(C4="","",IFERROR(VLOOKUP(C4,マスター!A:B,2,0),"")) | E4: =IF(C4="","",IFERROR(VLOOKUP(C4,マスター!A:C,3,0),"")) | H4: =IF(G4="","",G4*0.1) | I4: =IF(G4="","",G4+H4) | K4: =IF(J4="","",EOMONTH(J4,1)) | N4: =IF(C4="","",IF(L4<>"","支払済","未払"))
A5: =IF(C5<>"",ROW()-1,"") | D5: =IF(C5="","",IFERROR(VLOOKUP(C5,マスター!A:B,2,0),"")) | E5: =IF(C5="","",IFERROR(VLOOKUP(C5,マスター!A:C,3,0),"")) | H5: =IF(G5="","",G5*0.1) | I5: =IF(G5="","",G5+H5) | K5: =IF(J5="","",EOMONTH(J5,1)) | N5: =IF(C5="","",IF(L5<>"","支払済","未払"))
A6: =IF(C6<>"",ROW()-1,"") | D6: =IF(C6="","",IFERROR(VLOOKUP(C6,マスター!A:B,2,0),"")) | E6: =IF(C6="","",IFERROR(VLOOKUP(C6,マスター!A:C,3,0),"")) | H6: =IF(G6="","",G6*0.1) | I6: =IF(G6="","",G6+H6) | K6: =IF(J6="","",EOMONTH(J6,1)) | N6: =IF(C6="","",IF(L6<>"","支払済","未払"))
A7: =IF(C7<>"",ROW()-1,"") | D7: =IF(C7="","",IFERROR(VLOOKUP(C7,マスター!A:B,2,0),"")) | E7: =IF(C7="","",IFERROR(VLOOKUP(C7,マスター!A:C,3,0),"")) | H7: =IF(G7="","",G7*0.1) | I7: =IF(G7="","",G7+H7) | K7: =IF(J7="","",EOMONTH(J7,1)) | N7: =IF(C7="","",IF(L7<>"","支払済","未払"))
A8: =IF(C8<>"",ROW()-1,"") | D8: =IF(C8="","",IFERROR(VLOOKUP(C8,マスター!A:B,2,0),"")) | E8: =IF(C8="","",IFERROR(VLOOKUP(C8,マスター!A:C,3,0),"")) | H8: =IF(G8="","",G8*0.1) | I8: =IF(G8="","",G8+H8) | K8: =IF(J8="","",EOMONTH(J8,1)) | N8: =IF(C8="","",IF(L8<>"","支払済","未払"))
A9: =IF(C9<>"",ROW()-1,"") | D9: =IF(C9="","",IFERROR(VLOOKUP(C9,マスター!A:B,2,0),"")) | E9: =IF(C9="","",IFERROR(VLOOKUP(C9,マスター!A:C,3,0),"")) | H9: =IF(G9="","",G9*0.1) | I9: =IF(G9="","",G9+H9) | K9: =IF(J9="","",EOMONTH(J9,1)) | N9: =IF(C9="","",IF(L9<>"","支払済","未払"))
A10: =IF(C10<>"",ROW()-1,"") | D10: =IF(C10="","",IFERROR(VLOOKUP(C10,マスター!A:B,2,0),"")) | E10: =IF(C10="","",IFERROR(VLOOKUP(C10,マスター!A:C,3,0),"")) | H10: =IF(G10="","",G10*0.1) | I10: =IF(G10="","",G10+H10) | K10: =IF(J10="","",EOMONTH(J10,1)) | N10: =IF(C10="","",IF(L10<>"","支払済","未払"))
A11: =IF(C11<>"",ROW()-1,"") | D11: =IF(C11="","",IFERROR(VLOOKUP(C11,マスター!A:B,2,0),"")) | E11: =IF(C11="","",IFERROR(VLOOKUP(C11,マスター!A:C,3,0),"")) | H11: =IF(G11="","",G11*0.1) | I11: =IF(G11="","",G11+H11) | K11: =IF(J11="","",EOMONTH(J11,1)) | N11: =IF(C11="","",IF(L11<>"","支払済","未払"))
A12: =IF(C12<>"",ROW()-1,"") | D12: =IF(C12="","",IFERROR(VLOOKUP(C12,マスター!A:B,2,0),"")) | E12: =IF(C12="","",IFERROR(VLOOKUP(C12,マスター!A:C,3,0),"")) | H12: =IF(G12="","",G12*0.1) | I12: =IF(G12="","",G12+H12) | K12: =IF(J12="","",EOMONTH(J12,1)) | N12: =IF(C12="","",IF(L12<>"","支払済","未払"))
A13: =IF(C13<>"",ROW()-1,"") | D13: =IF(C13="","",IFERROR(VLOOKUP(C13,マスター!A:B,2,0),"")) | E13: =IF(C13="","",IFERROR(VLOOKUP(C13,マスター!A:C,3,0),"")) | H13: =IF(G13="","",G13*0.1) | I13: =IF(G13="","",G13+H13) | K13: =IF(J13="","",EOMONTH(J13,1)) | N13: =IF(C13="","",IF(L13<>"","支払済","未払"))
... A201: =IF(C201<>"",ROW()-1,"") | D201: =IF(C201="","",IFERROR(VLOOKUP(C201,マスター!A:B,2,0),"")) | E201: =IF(C201="","",IFERROR(VLOOKUP(C201,マスター!A:C,3,0),"")) | H201: =IF(G201="","",G201*0.1) | I201: =IF(G201="","",G201+H201) | K201: =IF(J201="","",EOMONTH(J201,1)) | N201: =IF(C201="","",IF(L201<>"","支払済","未払"))
F202: 合計 | G202: =SUM(G2:G201) | H202: =SUM(H2:H201) | I202: =SUM(I2:I201) | M202: =SUM(M2:M201) | N202: =COUNTIF(N2:N201,"未払")&"件未払"

Sheet 売上管理
A1: No | B1: 登録日 | C1: 得意先名 | D1: 案件名 | E1: 請求額(税抜) | F1: 消費税(10%) | G1: 合計(税込) | H1: 請求日 | I1: 入金期限 | J1: 入金日 | K1: 入金額 | L1: 状況
A2: =IF(C2<>"",ROW()-1,"") | F2: =IF(E2="","",E2*0.1) | G2: =IF(E2="","",E2+F2) | L2: =IF(C2="","",IF(J2="","未入金",IF(K2>=G2,"入金済","一部入金")))
A3: =IF(C3<>"",ROW()-1,"") | F3: =IF(E3="","",E3*0.1) | G3: =IF(E3="","",E3+F3) | L3: =IF(C3="","",IF(J3="","未入金",IF(K3>=G3,"入金済","一部入金")))
A4: =IF(C4<>"",ROW()-1,"") | F4: =IF(E4="","",E4*0.1) | G4: =IF(E4="","",E4+F4) | L4: =IF(C4="","",IF(J4="","未入金",IF(K4>=G4,"入金済","一部入金")))
A5: =IF(C5<>"",ROW()-1,"") | F5: =IF(E5="","",E5*0.1) | G5: =IF(E5="","",E5+F5) | L5: =IF(C5="","",IF(J5="","未入金",IF(K5>=G5,"入金済","一部入金")))
A6: =IF(C6<>"",ROW()-1,"") | F6: =IF(E6="","",E6*0.1) | G6: =IF(E6="","",E6+F6) | L6: =IF(C6="","",IF(J6="","未入金",IF(K6>=G6,"入金済","一部入金")))
A7: =IF(C7<>"",ROW()-1,"") | F7: =IF(E7="","",E7*0.1) | G7: =IF(E7="","",E7+F7) | L7: =IF(C7="","",IF(J7="","未入金",IF(K7>=G7,"入金済","一部入金")))
A8: =IF(C8<>"",ROW()-1,"") | F8: =IF(E8="","",E8*0.1) | G8: =IF(E8="","",E8+F8) | L8: =IF(C8="","",IF(J8="","未入金",IF(K8>=G8,"入金済","一部入金")))
A9: =IF(C9<>"",ROW()-1,"") | F9: =IF(E9="","",E9*0.1) | G9: =IF(E9="","",E9+F9) | L9: =IF(C9="","",IF(J9="","未入金",IF(K9>=G9,"入金済","一部入金")))
A10: =IF(C10<>"",ROW()-1,"") | F10: =IF(E10="","",E10*0.1) | G10: =IF(E10="","",E10+F10) | L10: =IF(C10="","",IF(J10="","未入金",IF(K10>=G10,"入金済","一部入金")))
A11: =IF(C11<>"",ROW()-1,"") | F11: =IF(E11="","",E11*0.1) | G11: =IF(E11="","",E11+F11) | L11: =IF(C11="","",IF(J11="","未入金",IF(K11>=G11,"入金済","一部入金")))
A12: =IF(C12<>"",ROW()-1,"") | F12: =IF(E12="","",E12*0.1) | G12: =IF(E12="","",E12+F12) | L12: =IF(C12="","",IF(J12="","未入金",IF(K12>=G12,"入金済","一部入金")))
A13: =IF(C13<>"",ROW()-1,"") | F13: =IF(E13="","",E13*0.1) | G13: =IF(E13="","",E13+F13) | L13: =IF(C13="","",IF(J13="","未入金",IF(K13>=G13,"入金済","一部入金")))
... A201: =IF(C201<>"",ROW()-1,"") | F201: =IF(E201="","",E201*0.1) | G201: =IF(E201="","",E201+F201) | L201: =IF(C201="","",IF(J201="","未入金",IF(K201>=G201,"入金済","一部入金")))
D202: 合計 | E202: =SUM(E2:E201) | F202: =SUM(F2:F201) | G202: =SUM(G2:G201) | K202: =SUM(K2:K201) | L202: =COUNTIF(L2:L201,"未入金")&"件未入金"

Sheet 人件費
A1: 社員名 | B1: 支給総額 | C1: 控除合計 | D1: 手取り | E1: 支払日 | F1: 備考
A2: 野添優 | D2: =IF(B2="","",B2-C2)
A3: 丸田翔吾 | D3: =IF(B3="","",B3-C3)
D4: =IF(B4="","",B4-C4)
D5: =IF(B5="","",B5-C5)
D6: =IF(B6="","",B6-C6)
D7: =IF(B7="","",B7-C7)
D8: =IF(B8="","",B8-C8)
D9: =IF(B9="","",B9-C9)
D10: =IF(B10="","",B10-C10)
D11: =IF(B11="","",B11-C11)
A15: 合計 | B15: =SUM(B2:B14) | C15: =SUM(C2:C14) | D15: =SUM(D2:D14)

Sheet マスター
A1: 業者名 | B1: 種別 | C1: インボイス | E1: 得意先名 | G1: 経費種類
A2: 梶原通信 | B2: 個人 | C2: あり | E2: 港振興業株式会社 | G2: 材料費
A3: 秀電工 | B3: 個人 | C3: あり | E3: 株式会社トラストテクノス | G3: 燃料費
A4: 井本貴史 | B4: 個人 | C4: なし | E4: 有限会社平成システム | G4: 高速料金
A5: LLS電気 | B5: 個人 | C5: あり | E5: FGE合同会社 | G5: 駐車場代
A6: 株式会社トラストテクノス | B6: 法人 | C6: あり | E6: mtr株式会社 | G6: 工具・消耗品費
A7: 株式会社RISE | B7: 法人 | C7: あり | E7: 株式会社オークコミュニケーション | G7: 通信費
E8: 株式会社ライズ | G8: 交際費
E9: 千里スカイハイツ管理組合 | G9: 会議費
E10: 菊次 | G10: 事務用品費
E11: ページ | G11: 広告宣伝費
G12: 研修費
G13: 福利厚生費
G14: 車両維持費
G15: 地代家賃
G16: 保険料
G17: 雑費
